AutoGitSemVer/AutoGitSemVerSchema.json
AutoGitSemVer/EntryPoint.py
AutoGitSemVer/Lib.py
AutoGitSemVer/__init__.py
AutoGitSemVer/py.typed
AutoGitSemVer/scripts/UpdatePythonVersion.py
AutoGitSemVer/scripts/__init__.py
autogitsemver-0.9.2.dist-info/WHEEL
autogitsemver-0.9.2.dist-info/entry_points.txt
autogitsemver-0.9.2.dist-info/METADATA
autogitsemver-0.9.2.dist-info/RECORD
