Metadata-Version: 2.3
Name: autogitsemver
Version: 0.9.2
Summary: Generate a semantic version based on commits made to a git repository.
Author: David Brownell
Author-email: David Brownell <github@DavidBrownell.com>
License: MIT
Classifier: Development Status :: 4 - Beta
Classifier: Intended Audience :: Developers
Classifier: Natural Language :: English
Classifier: Operating System :: MacOS
Classifier: Operating System :: Microsoft :: Windows
Classifier: Operating System :: POSIX :: Linux
Classifier: Programming Language :: Python
Classifier: Programming Language :: Python :: 3.13
Classifier: Programming Language :: Python :: 3.12
Classifier: Programming Language :: Python :: 3.11
Classifier: Programming Language :: Python :: 3.10
Classifier: Topic :: Software Development
Classifier: Topic :: System :: System Shells
Classifier: Topic :: Terminals
Classifier: Topic :: Utilities
Requires-Dist: dbrownell-common>=0.14.6
Requires-Dist: gitpython>=3.1.44
Requires-Dist: jsonschema>=4.23.0
Requires-Dist: rtyaml>=1.0.0
Requires-Dist: semantic-version>=2.10.0
Requires-Python: >=3.10
Project-URL: Documentation, https://github.com/davidbrownell/AutoGitSemVer
Project-URL: Homepage, https://github.com/davidbrownell/AutoGitSemVer
Project-URL: Repository, https://github.com/davidbrownell/AutoGitSemVer
